byted_overpass_ad_actor_review_doc_verify/__init__.py
byted_overpass_ad_actor_review_doc_verify-0.0.1.dist-info/METADATA
byted_overpass_ad_actor_review_doc_verify-0.0.1.dist-info/WHEEL
byted_overpass_ad_actor_review_doc_verify-0.0.1.dist-info/top_level.txt
byted_overpass_ad_actor_review_doc_verify-0.0.1.dist-info/RECORD
